aiida_common_workflows/__init__.py
aiida_common_workflows/cli/__init__.py
aiida_common_workflows/cli/launch.py
aiida_common_workflows/cli/options.py
aiida_common_workflows/cli/plot.py
aiida_common_workflows/cli/root.py
aiida_common_workflows/cli/utils.py
aiida_common_workflows/common/__init__.py
aiida_common_workflows/common/types.py
aiida_common_workflows/common/data/Al.cif
aiida_common_workflows/common/data/Fe.cif
aiida_common_workflows/common/data/GeTe.cif
aiida_common_workflows/common/data/README
aiida_common_workflows/common/data/Si.cif
aiida_common_workflows/common/data/h2.xyz
aiida_common_workflows/common/data/nh3_cone.xyz
aiida_common_workflows/common/data/nh3_flat.xyz
aiida_common_workflows/common/visualization/__init__.py
aiida_common_workflows/common/visualization/dissociation.py
aiida_common_workflows/common/visualization/eos.py
aiida_common_workflows/generators/__init__.py
aiida_common_workflows/generators/generator.py
aiida_common_workflows/generators/ports.py
aiida_common_workflows/generators/spec.py
aiida_common_workflows/plugins/__init__.py
aiida_common_workflows/plugins/entry_point.py
aiida_common_workflows/protocol/__init__.py
aiida_common_workflows/protocol/registry.py
aiida_common_workflows/utils/__init__.py
aiida_common_workflows/utils/sphinx_extension/__init__.py
aiida_common_workflows/utils/sphinx_extension/input_generator.py
aiida_common_workflows/workflows/__init__.py
aiida_common_workflows/workflows/dissociation.py
aiida_common_workflows/workflows/eos.py
aiida_common_workflows/workflows/bands/__init__.py
aiida_common_workflows/workflows/bands/generator.py
aiida_common_workflows/workflows/bands/workchain.py
aiida_common_workflows/workflows/bands/siesta/__init__.py
aiida_common_workflows/workflows/bands/siesta/generator.py
aiida_common_workflows/workflows/bands/siesta/workchain.py
aiida_common_workflows/workflows/relax/__init__.py
aiida_common_workflows/workflows/relax/generator.py
aiida_common_workflows/workflows/relax/workchain.py
aiida_common_workflows-1.0.1.dist-info/entry_points.txt
aiida_common_workflows-1.0.1.dist-info/LICENSE.txt
aiida_common_workflows-1.0.1.dist-info/WHEEL
aiida_common_workflows-1.0.1.dist-info/METADATA
aiida_common_workflows-1.0.1.dist-info/RECORD
