Metadata-Version: 2.1
Name: aiida-common-workflows
Version: 1.0.1
Summary: Package that defines common interfaces for workflows that are implemented in AiiDA for various quantum engines.
Keywords: aiida,workflows
Author-email: The AiiDA team <developers@aiida.net>
Requires-Python: >=3.8,<3.10
Classifier: Development Status :: 4 - Beta
Classifier: Framework :: AiiDA
Classifier: License :: OSI Approved :: MIT License
Classifier: Operating System :: POSIX :: Linux
Classifier: Operating System :: MacOS :: MacOS X
Classifier: Programming Language :: Python
Classifier: Programming Language :: Python :: 3.8
Classifier: Programming Language :: Python :: 3.9
Requires-Dist: abipy==0.9.6
Requires-Dist: aiida-abinit~=0.4.0
Requires-Dist: aiida-bigdft>=0.2.6
Requires-Dist: aiida-castep>=1.2.0a5
Requires-Dist: aiida-core[atomic_tools]~=1.6
Requires-Dist: aiida-cp2k~=1.6
Requires-Dist: aiida-fleur>=1.3.0
Requires-Dist: aiida-gaussian
Requires-Dist: aiida-nwchem>=2.1.0
Requires-Dist: aiida-orca
Requires-Dist: aiida-pseudo==0.6.5
Requires-Dist: aiida-quantumespresso~=3.4,>=3.4.1
Requires-Dist: aiida-siesta>=1.2.0
Requires-Dist: aiida-vasp~=2.2
Requires-Dist: aiida-wien2k~=0.1.1
Requires-Dist: aiida-ase
Requires-Dist: pymatgen>=2022.1.20
Requires-Dist: numpy<1.24.0
Requires-Dist: sqlalchemy<1.4
Requires-Dist: ase!=3.20.*
Requires-Dist: pint~=0.16
Requires-Dist: masci-tools~=0.9
Requires-Dist: docutils~=0.15.2 ; extra == "docs"
Requires-Dist: pygments~=2.5 ; extra == "docs"
Requires-Dist: pydata-sphinx-theme~=0.4.0 ; extra == "docs"
Requires-Dist: sphinx~=3.2 ; extra == "docs"
Requires-Dist: sphinx-panels~=0.5.0 ; extra == "docs"
Requires-Dist: sphinxcontrib-details-directive~=0.1.0 ; extra == "docs"
Requires-Dist: sphinx-copybutton~=0.3.0 ; extra == "docs"
Requires-Dist: pre-commit~=2.2 ; extra == "pre-commit"
Requires-Dist: pylint~=2.5.2 ; extra == "pre-commit"
Requires-Dist: pytest~=7.2 ; extra == "tests"
Requires-Dist: pgtest~=1.3,>=1.3.1 ; extra == "tests"
Requires-Dist: pytest-regressions~=1.0 ; extra == "tests"
Project-URL: Documentation, https://aiida-common-workflows.readthedocs.io
Project-URL: Home, https://github.com/aiidateam/aiida-common-workflows
Project-URL: Source, https://github.com/aiidateam/aiida-common-workflows
Provides-Extra: docs
Provides-Extra: pre-commit
Provides-Extra: tests
